fn_reflection/__init__.py
fn_reflection/algorithm.py
fn_reflection/collections.py
fn_reflection/data_format.py
fn_reflection/debug.py
fn_reflection/mail.py
fn_reflection/os.py
fn_reflection/sys.py
fn_reflection/time.py
fn_reflection/tsm.py
fn_reflection-1.0.7.dist-info/LICENCE
fn_reflection-1.0.7.dist-info/METADATA
fn_reflection-1.0.7.dist-info/WHEEL
fn_reflection-1.0.7.dist-info/top_level.txt
fn_reflection-1.0.7.dist-info/RECORD
